MANIFEST.in
README.md
setup.py
sqlbatis/__init__.py
sqlbatis/_internals.py
sqlbatis/cli.py
sqlbatis/connection.py
sqlbatis/container.py
sqlbatis/dynamic_sql_builder.py
sqlbatis/errors.py
sqlbatis/model.py
sqlbatis/page_query_builder.py
sqlbatis/row.py
sqlbatis/scanner.py
sqlbatis/sqlbatis.py
sqlbatis/sqlbatis_dao.py
sqlbatis/utils.py
sqlbatis.egg-info/PKG-INFO
sqlbatis.egg-info/SOURCES.txt
sqlbatis.egg-info/dependency_links.txt
sqlbatis.egg-info/entry_points.txt
sqlbatis.egg-info/requires.txt
sqlbatis.egg-info/top_level.txt
sqlbatis/template/alembic.ini.mako
sqlbatis/template/env.py.mako
tests/__init__.py
tests/basic_test.py
tests/crud.py
tests/test_basic_dao.py
tests/test_bulk_query.py
tests/test_db_query.py
tests/test_decorators_on_class.py
tests/test_dynamic_sql_builder.py
tests/test_filter_by.py
tests/test_proxy.py
tests/test_query_by_page.py
tests/test_query_on_class.py
tests/test_row.py
tests/test_row_set.py
tests/test_transaction.py
tests/test_transaction_required.py