Metadata-Version: 2.1
Name: sqlbatis
Version: 0.9.0
Summary: A tool that help u to interact with DB more easily
Home-page: UNKNOWN
Author: Leo
Author-email: leo.anonymous@qq.com
License: UNKNOWN
Platform: UNKNOWN
